net_dl/__init__.py
net_dl/__main__.py
net_dl/config.py
net_dl/download.py
net_dl/props.py
net_dl-0.2.3.dist-info/LICENSE.txt
net_dl-0.2.3.dist-info/METADATA
net_dl-0.2.3.dist-info/WHEEL
net_dl-0.2.3.dist-info/entry_points.txt
net_dl-0.2.3.dist-info/top_level.txt
net_dl-0.2.3.dist-info/RECORD
