Metadata-Version: 2.1
Name: net-dl
Version: 0.2.3
Summary: Download web pages and files from the internet using CLI or as a Python module.
Author-email: Nate Marti <nate_marti@sil.org>
Project-URL: Homepage, https://sil-car.github.io/net-dl/
Project-URL: Issues, https://github.com/sil-car/net-dl/issues
Classifier: Programming Language :: Python :: 3
Classifier: License :: OSI Approved :: MIT License
Classifier: Operating System :: OS Independent
Requires-Python: >=3.8
License-File: LICENSE.txt
Requires-Dist: requests
Provides-Extra: docs
Requires-Dist: sphinx; extra == "docs"
Requires-Dist: sphinx-autoapi; extra == "docs"
